channels_graphql_ws/__init__.py
channels_graphql_ws/client.py
channels_graphql_ws/graphql_ws_consumer.py
channels_graphql_ws/scope_as_context.py
channels_graphql_ws/serializer.py
channels_graphql_ws/subscription.py
channels_graphql_ws/testing.py
channels_graphql_ws/transport.py
django_channels_graphql_ws_django4-0.9.3.dist-info/LICENSE
django_channels_graphql_ws_django4-0.9.3.dist-info/WHEEL
django_channels_graphql_ws_django4-0.9.3.dist-info/METADATA
django_channels_graphql_ws_django4-0.9.3.dist-info/RECORD
