Metadata-Version: 2.1
Name: django-channels-graphql-ws-django4
Version: 0.9.3
Summary: Django Channels based WebSocket GraphQL server with Graphene-like subscriptions
Home-page: https://github.com/datadvance/DjangoChannelsGraphqlWs
License: MIT
Author: Alexander A. Prokhorov
Author-email: alexander.prokhorov@datadvance.net
Requires-Python: >=3.8.0
Classifier: License :: OSI Approved :: MIT License
Classifier: Programming Language :: Python :: 3
Classifier: Programming Language :: Python :: 3.8
Classifier: Programming Language :: Python :: 3.9
Classifier: Programming Language :: Python :: 3.10
Classifier: Programming Language :: Python :: 3.11
Requires-Dist: Django
Requires-Dist: aiohttp (>=3,<4)
Requires-Dist: asgiref
Requires-Dist: channels (>=3)
Requires-Dist: graphene (>=2.1)
Requires-Dist: graphql-core (>=2.2)
Requires-Dist: msgpack (>=0.6.1,<2)
Project-URL: Repository, https://github.com/datadvance/DjangoChannelsGraphqlWs
